{"event_details":{"event_id":"5247687","url":"https://zwiftpower.com/events.php?zid=5247687","title":"🚴‍♀❄ Masters Winter Tour - Stage 7 ❄🚴‍♀","start_time":"2026-02-13 18:20:00","route":"Sprinter's Playground","distance":"24.7 km","elevation":"131 m","laps":"2 Laps","description":"🚴‍♀❄ Masters Winter Tour 2025/26 by Team INOX ❄🚴‍♀\n18 Stage • Total distance 391.7 km • Total difference in altitude 4150 m\nMAKE SURE YOU MEET ALL REQUIREMENTS TO AVOID DISQUALIFICATION\n• Heart rate monitors are mandatory for podium positions.\n• Smart trainers or power meters must be connected as the power source.\n• You must have an active ZwiftPower account at\nhttps://zwiftpower.com\n• Enter the correct age based category pen.\n🏁 CATEGORIES\nTo ensure a fair and balanced competition, all pens start simultaneously, and all riders are visible to each other.\nThe 5 starting categories are based on age:\nElite (Cat A) → up to 29 years old\nM30 (Cat B) → 30–39 years\nM40 (Cat C) → 40–49 years\nM50 (Cat D) → 50–59 years\nM60 (Cat E) → 60+ years\n⚙️ RACE SETTINGS\nBike Upgrades: ENABLED\nSteering: ENABLED\nPower Ups: NONE\nJersey Unlock: FREESPEED\n🏆 RANKINGS & SCORING\n• Individual Time Ranking: The overall ranking will be based on the total time accumulated in all races. In case of absence, the time of the last classified rider will be assigned.\n• Points: Valid points will be awarded according to the FIN, FTS, and FAL criteria, to reward both 10 best sprinters and climbers.\nTimes, rankings, points will always be updated and available on our website\n⚠️ NOTES & CONDUCT\nFurther information will be shared promptly via Discord and Facebook.\nThe organizers reserve the right to review results and disqualify riders in case of suspected misconduct.\n💬 CONTACT US\n• Website:\nhttps://www.teaminox.it/\n• Facebook Page:\nhttps://www.facebook.com/groups/inoxteam/\n• Zwift Companion Club:\nhttps://www.zwift.com/uk/clubs/cef70cde ... 44703/home\n• Discord Channel:\nhttps://discord.gg/cpr3rBGaZy\n• ZwiftPower:\nteam.php?id=16461\n• STRAVA:\nhttps://strava.app.link/p2Oj6TaE3Gb\nEveryone is Welcome! 🙏🏻"},"race_results":[{"category":"B","name":"Merlin Dallaire[5.W.4.T]","tname":"5.W.4.T","zwid":3003593,"pos":1,"fal":92,"fts":96,"fin":80,"total":268,"time":1983.147,"pts_sprint":188,"pts_kom":0,"tempo_pos":2,"tempo_time":1983.147,"tempo_points":268,"sprinter_pos":1,"sprinter_total_race_points":268},{"category":"B","name":"Alexandre  MASSARDIER ","tname":"&#9889;&#65039;Team Foudre&#9889;&#65039;","zwid":5247405,"pos":2,"fal":92,"fts":70,"fin":100,"total":262,"time":1975.98,"pts_sprint":162,"pts_kom":0,"tempo_pos":1,"tempo_time":1975.98,"tempo_points":262,"sprinter_pos":2,"sprinter_total_race_points":262},{"category":"B","name":"paul spadaro [INOX]","tname":"INOX","zwid":6117581,"pos":3,"fal":32,"fts":80,"fin":60,"total":172,"time":2180.456,"pts_sprint":112,"pts_kom":0,"tempo_pos":4,"tempo_time":2180.456,"tempo_points":172,"sprinter_pos":3,"sprinter_total_race_points":172},{"category":"B","name":"Paul Tautorat","tname":"","zwid":3062801,"pos":4,"fal":65,"fts":47,"fin":50,"total":162,"time":2181.993,"pts_sprint":112,"pts_kom":0,"tempo_pos":6,"tempo_time":2181.993,"tempo_points":162,"sprinter_pos":4,"sprinter_total_race_points":162},{"category":"B","name":"D &eacute;j&agrave; Stu","tname":"","zwid":7611806,"pos":5,"fal":53,"fts":37,"fin":70,"total":160,"time":2180.18,"pts_sprint":90,"pts_kom":0,"tempo_pos":3,"tempo_time":2180.18,"tempo_points":160,"sprinter_pos":5,"sprinter_total_race_points":160},{"category":"B","name":"Joost Bloemberg","tname":"","zwid":3156448,"pos":6,"fal":39,"fts":35,"fin":55,"total":129,"time":2181.681,"pts_sprint":74,"pts_kom":0,"tempo_pos":5,"tempo_time":2181.681,"tempo_points":129,"sprinter_pos":7,"sprinter_total_race_points":129},{"category":"B","name":"Baptiste Mauro","tname":"","zwid":3481080,"pos":7,"fal":35,"fts":43,"fin":45,"total":123,"time":2182.433,"pts_sprint":78,"pts_kom":0,"tempo_pos":7,"tempo_time":2182.433,"tempo_points":123,"sprinter_pos":6,"sprinter_total_race_points":123},{"category":"B","name":"Aur&eacute;lien Janvier","tname":"","zwid":7604569,"pos":8,"fal":0,"fts":4,"fin":0,"total":4,"time":0,"pts_sprint":4,"pts_kom":0,"tempo_pos":8,"tempo_time":0,"tempo_points":4,"sprinter_pos":8,"sprinter_total_race_points":4},{"category":"C","name":"Oliver Milk","tname":"Wahoo Esports","zwid":50486,"pos":1,"fal":100,"fts":96,"fin":80,"total":276,"time":1982.076,"pts_sprint":196,"pts_kom":0,"tempo_pos":2,"tempo_time":1982.076,"tempo_points":276,"sprinter_pos":1,"sprinter_total_race_points":276},{"category":"C","name":"Tim Cartwright","tname":"COALITION","zwid":125622,"pos":2,"fal":66,"fts":36,"fin":100,"total":202,"time":1967.579,"pts_sprint":102,"pts_kom":0,"tempo_pos":1,"tempo_time":1967.579,"tempo_points":202,"sprinter_pos":4,"sprinter_total_race_points":202},{"category":"C","name":"jean Fran&ccedil;ois Kohl (foudre)","tname":"&#9889;&#65039;Team Foudre&#9889;&#65039;","zwid":3401875,"pos":3,"fal":54,"fts":84,"fin":45,"total":183,"time":2179.688,"pts_sprint":138,"pts_kom":0,"tempo_pos":7,"tempo_time":2179.688,"tempo_points":183,"sprinter_pos":2,"sprinter_total_race_points":183},{"category":"C","name":"Guido Lamet","tname":"INOX","zwid":5965851,"pos":4,"fal":66,"fts":53,"fin":60,"total":179,"time":1982.477,"pts_sprint":119,"pts_kom":0,"tempo_pos":4,"tempo_time":1982.477,"tempo_points":179,"sprinter_pos":3,"sprinter_total_race_points":179},{"category":"C","name":"GAVIN ARBER ONYX RT","tname":"Onyx","zwid":606,"pos":5,"fal":60,"fts":38,"fin":70,"total":168,"time":1982.297,"pts_sprint":98,"pts_kom":0,"tempo_pos":3,"tempo_time":1982.297,"tempo_points":168,"sprinter_pos":5,"sprinter_total_race_points":168},{"category":"C","name":"JV Allstar","tname":"DIRT","zwid":4658861,"pos":6,"fal":30,"fts":46,"fin":40,"total":116,"time":2180.549,"pts_sprint":76,"pts_kom":0,"tempo_pos":8,"tempo_time":2180.549,"tempo_points":116,"sprinter_pos":6,"sprinter_total_race_points":116},{"category":"C","name":"Adam Pryjomski","tname":"LEVEL Esports","zwid":446528,"pos":7,"fal":12,"fts":11,"fin":50,"total":73,"time":2178.905,"pts_sprint":23,"pts_kom":0,"tempo_pos":6,"tempo_time":2178.905,"tempo_points":73,"sprinter_pos":9,"sprinter_total_race_points":73},{"category":"C","name":"Taco Jellema","tname":"RMDB","zwid":4382571,"pos":8,"fal":8,"fts":8,"fin":55,"total":71,"time":2178.696,"pts_sprint":16,"pts_kom":0,"tempo_pos":5,"tempo_time":2178.696,"tempo_points":71,"sprinter_pos":10,"sprinter_total_race_points":71},{"category":"C","name":"Nicolas Buffet","tname":"","zwid":5459654,"pos":9,"fal":18,"fts":17,"fin":36,"total":71,"time":2180.569,"pts_sprint":35,"pts_kom":0,"tempo_pos":9,"tempo_time":2180.569,"tempo_points":71,"sprinter_pos":8,"sprinter_total_race_points":71},{"category":"C","name":"Luca Pozzani [SRT5]","tname":"S R T","zwid":3494138,"pos":10,"fal":8,"fts":7,"fin":32,"total":47,"time":2181.315,"pts_sprint":15,"pts_kom":0,"tempo_pos":10,"tempo_time":2181.315,"tempo_points":47,"sprinter_pos":11,"sprinter_total_race_points":47},{"category":"C","name":"Francesco Ravasi [INOX]","tname":"INOX","zwid":3617605,"pos":11,"fal":0,"fts":14,"fin":29,"total":43,"time":2471.808,"pts_sprint":14,"pts_kom":0,"tempo_pos":11,"tempo_time":2471.808,"tempo_points":43,"sprinter_pos":12,"sprinter_total_race_points":43},{"category":"C","name":"Luca Miggiano [ITA]","tname":"","zwid":1005113,"pos":12,"fal":14,"fts":25,"fin":0,"total":39,"time":0,"pts_sprint":39,"pts_kom":0,"tempo_pos":16,"tempo_time":0,"tempo_points":39,"sprinter_pos":7,"sprinter_total_race_points":39},{"category":"C","name":"Mr Zwifter","tname":"","zwid":5242229,"pos":13,"fal":0,"fts":0,"fin":26,"total":26,"time":2472.971,"pts_sprint":0,"pts_kom":0,"tempo_pos":12,"tempo_time":2472.971,"tempo_points":26},{"category":"C","name":"Aidan Waterbury","tname":"","zwid":6694790,"pos":14,"fal":0,"fts":0,"fin":24,"total":24,"time":2686.362,"pts_sprint":0,"pts_kom":0,"tempo_pos":13,"tempo_time":2686.362,"tempo_points":24},{"category":"C","name":"David Tripp (SWIM 1ST) ","tname":"TFC","zwid":114069,"pos":15,"fal":0,"fts":0,"fin":22,"total":22,"time":2706.841,"pts_sprint":0,"pts_kom":0,"tempo_pos":14,"tempo_time":2706.841,"tempo_points":22},{"category":"C","name":"Ozzy Kay","tname":"","zwid":7904245,"pos":16,"fal":0,"fts":0,"fin":20,"total":20,"time":2738.389,"pts_sprint":0,"pts_kom":0,"tempo_pos":15,"tempo_time":2738.389,"tempo_points":20},{"category":"C","name":"Geo Law","tname":"","zwid":3081588,"pos":17,"fal":0,"fts":1,"fin":0,"total":1,"time":0,"pts_sprint":1,"pts_kom":0,"tempo_pos":17,"tempo_time":0,"tempo_points":1,"sprinter_pos":13,"sprinter_total_race_points":1},{"category":"D","name":"Marzio Vanoni [TSE]","tname":"TSE","zwid":706065,"pos":1,"fal":78,"fts":60,"fin":70,"total":208,"time":1968.246,"pts_sprint":138,"pts_kom":0,"tempo_pos":3,"tempo_time":1968.246,"tempo_points":208,"sprinter_pos":1,"sprinter_total_race_points":208},{"category":"D","name":"STEPHANE IRAOLA ","tname":"PETA-Z","zwid":1073129,"pos":2,"fal":51,"fts":54,"fin":100,"total":205,"time":1967.131,"pts_sprint":105,"pts_kom":0,"tempo_pos":1,"tempo_time":1967.131,"tempo_points":205,"sprinter_pos":3,"sprinter_total_race_points":205},{"category":"D","name":" David Cotin  ","tname":"&#9889;&#65039;Team Foudre&#9889;&#65039;","zwid":1527608,"pos":3,"fal":57,"fts":47,"fin":80,"total":184,"time":1967.759,"pts_sprint":104,"pts_kom":0,"tempo_pos":2,"tempo_time":1967.759,"tempo_points":184,"sprinter_pos":4,"sprinter_total_race_points":184},{"category":"D","name":"Rolf Trovato [WattFabrik] ","tname":"WATTFabrik","zwid":1419061,"pos":4,"fal":60,"fts":56,"fin":40,"total":156,"time":1982.899,"pts_sprint":116,"pts_kom":0,"tempo_pos":8,"tempo_time":1982.899,"tempo_points":156,"sprinter_pos":2,"sprinter_total_race_points":156},{"category":"D","name":"Cristian Collesei [INOX]","tname":"INOX","zwid":3092045,"pos":5,"fal":43,"fts":55,"fin":36,"total":134,"time":1984.472,"pts_sprint":98,"pts_kom":0,"tempo_pos":9,"tempo_time":1984.472,"tempo_points":134,"sprinter_pos":6,"sprinter_total_race_points":134},{"category":"D","name":"Rich Babbage (Exeter WCC)","tname":"EWCC","zwid":28524,"pos":6,"fal":64,"fts":36,"fin":32,"total":132,"time":1985.128,"pts_sprint":100,"pts_kom":0,"tempo_pos":10,"tempo_time":1985.128,"tempo_points":132,"sprinter_pos":5,"sprinter_total_race_points":132},{"category":"D","name":"T.   Campag","tname":"","zwid":3065342,"pos":7,"fal":33,"fts":25,"fin":50,"total":108,"time":1982.521,"pts_sprint":58,"pts_kom":0,"tempo_pos":6,"tempo_time":1982.521,"tempo_points":108,"sprinter_pos":8,"sprinter_total_race_points":108},{"category":"D","name":"Morten Andersen [eCKD] #KS#","tname":"eCKD","zwid":6241944,"pos":8,"fal":18,"fts":41,"fin":45,"total":104,"time":1982.693,"pts_sprint":59,"pts_kom":0,"tempo_pos":7,"tempo_time":1982.693,"tempo_points":104,"sprinter_pos":7,"sprinter_total_race_points":104},{"category":"D","name":"Ale Raviolo [TSE]","tname":"TSE","zwid":4325085,"pos":9,"fal":10,"fts":16,"fin":55,"total":81,"time":1982.023,"pts_sprint":26,"pts_kom":0,"tempo_pos":5,"tempo_time":1982.023,"tempo_points":81,"sprinter_pos":10,"sprinter_total_race_points":81},{"category":"D","name":"GT 72 (TSE)","tname":"TSE","zwid":420226,"pos":10,"fal":5,"fts":10,"fin":60,"total":75,"time":1981.865,"pts_sprint":15,"pts_kom":0,"tempo_pos":4,"tempo_time":1981.865,"tempo_points":75,"sprinter_pos":12,"sprinter_total_race_points":75},{"category":"D","name":"Norberto Civardi","tname":"INOX","zwid":296309,"pos":11,"fal":0,"fts":29,"fin":22,"total":51,"time":2180.801,"pts_sprint":29,"pts_kom":0,"tempo_pos":14,"tempo_time":2180.801,"tempo_points":51,"sprinter_pos":9,"sprinter_total_race_points":51},{"category":"D","name":"Brian Barnes (SWX)","tname":"SWX","zwid":847605,"pos":12,"fal":11,"fts":6,"fin":24,"total":41,"time":2180.27,"pts_sprint":17,"pts_kom":0,"tempo_pos":13,"tempo_time":2180.27,"tempo_points":41,"sprinter_pos":11,"sprinter_total_race_points":41},{"category":"D","name":"  Stuie D","tname":"NZBRO ","zwid":3155363,"pos":13,"fal":6,"fts":1,"fin":29,"total":36,"time":2078.219,"pts_sprint":7,"pts_kom":0,"tempo_pos":11,"tempo_time":2078.219,"tempo_points":36,"sprinter_pos":13,"sprinter_total_race_points":36},{"category":"D","name":"Dean Eason (EM/SNCC)","tname":"ART","zwid":2479870,"pos":14,"fal":0,"fts":0,"fin":26,"total":26,"time":2178.353,"pts_sprint":0,"pts_kom":0,"tempo_pos":12,"tempo_time":2178.353,"tempo_points":26},{"category":"D","name":"Phillip Oliver (BL13)","tname":"BL13","zwid":76196,"pos":15,"fal":0,"fts":0,"fin":20,"total":20,"time":2180.835,"pts_sprint":0,"pts_kom":0,"tempo_pos":15,"tempo_time":2180.835,"tempo_points":20},{"category":"D","name":"Doug Smith","tname":"","zwid":3616583,"pos":16,"fal":0,"fts":0,"fin":18,"total":18,"time":2181.458,"pts_sprint":0,"pts_kom":0,"tempo_pos":16,"tempo_time":2181.458,"tempo_points":18},{"category":"D","name":"Stewart White","tname":"TFC","zwid":19537,"pos":17,"fal":0,"fts":0,"fin":16,"total":16,"time":2182.198,"pts_sprint":0,"pts_kom":0,"tempo_pos":17,"tempo_time":2182.198,"tempo_points":16},{"category":"D","name":"Tony Howard (Inox)","tname":"INOX","zwid":1141125,"pos":18,"fal":0,"fts":0,"fin":14,"total":14,"time":2182.987,"pts_sprint":0,"pts_kom":0,"tempo_pos":18,"tempo_time":2182.987,"tempo_points":14},{"category":"D","name":"A J (inox madness)","tname":"INOX","zwid":1120055,"pos":19,"fal":0,"fts":0,"fin":12,"total":12,"time":2445.166,"pts_sprint":0,"pts_kom":0,"tempo_pos":19,"tempo_time":2445.166,"tempo_points":12},{"category":"D","name":"Harm Cop","tname":"","zwid":255786,"pos":20,"fal":0,"fts":0,"fin":10,"total":10,"time":2471.743,"pts_sprint":0,"pts_kom":0,"tempo_pos":20,"tempo_time":2471.743,"tempo_points":10},{"category":"D","name":"Gerry Walsh","tname":"","zwid":290474,"pos":21,"fal":0,"fts":0,"fin":0,"total":0,"time":0,"pts_sprint":0,"pts_kom":0,"tempo_pos":21,"tempo_time":0,"tempo_points":0},{"category":"E","name":"Miky Tedesco [INOX]","tname":"INOX","zwid":1152951,"pos":1,"fal":100,"fts":88,"fin":100,"total":288,"time":1980.336,"pts_sprint":188,"pts_kom":0,"tempo_pos":1,"tempo_time":1980.336,"tempo_points":288,"sprinter_pos":1,"sprinter_total_race_points":288},{"category":"E","name":"Albert Chan (OTR)(UV)CRP","tname":"OTR Racing","zwid":492994,"pos":2,"fal":77,"fts":49,"fin":70,"total":196,"time":2180.705,"pts_sprint":126,"pts_kom":0,"tempo_pos":3,"tempo_time":2180.705,"tempo_points":196,"sprinter_pos":3,"sprinter_total_race_points":196},{"category":"E","name":" Roberto Baroni [ INOX ]","tname":"INOX","zwid":2975361,"pos":3,"fal":69,"fts":65,"fin":55,"total":189,"time":2181.567,"pts_sprint":134,"pts_kom":0,"tempo_pos":5,"tempo_time":2181.567,"tempo_points":189,"sprinter_pos":2,"sprinter_total_race_points":189},{"category":"E","name":"J. Russ Miears ","tname":"RXC","zwid":3362415,"pos":4,"fal":59,"fts":38,"fin":80,"total":177,"time":2180.111,"pts_sprint":97,"pts_kom":0,"tempo_pos":2,"tempo_time":2180.111,"tempo_points":177,"sprinter_pos":5,"sprinter_total_race_points":177},{"category":"E","name":"Dave Lancaster TBG","tname":"TBG","zwid":115130,"pos":5,"fal":18,"fts":92,"fin":40,"total":150,"time":2441.012,"pts_sprint":110,"pts_kom":0,"tempo_pos":8,"tempo_time":2441.012,"tempo_points":150,"sprinter_pos":4,"sprinter_total_race_points":150},{"category":"E","name":"Luca Briccoli [INOX]","tname":"INOX","zwid":1842490,"pos":6,"fal":41,"fts":47,"fin":50,"total":138,"time":2184.197,"pts_sprint":88,"pts_kom":0,"tempo_pos":6,"tempo_time":2184.197,"tempo_points":138,"sprinter_pos":6,"sprinter_total_race_points":138},{"category":"E","name":"Mel. Blackford  ","tname":"","zwid":1862589,"pos":7,"fal":38,"fts":29,"fin":60,"total":127,"time":2181.005,"pts_sprint":67,"pts_kom":0,"tempo_pos":4,"tempo_time":2181.005,"tempo_points":127,"sprinter_pos":7,"sprinter_total_race_points":127},{"category":"E","name":"Claudio Varo [INOX]","tname":"INOX","zwid":1992085,"pos":8,"fal":22,"fts":12,"fin":45,"total":79,"time":2384.494,"pts_sprint":34,"pts_kom":0,"tempo_pos":7,"tempo_time":2384.494,"tempo_points":79,"sprinter_pos":8,"sprinter_total_race_points":79},{"category":"E","name":"David Axson","tname":"","zwid":3238290,"pos":9,"fal":6,"fts":7,"fin":36,"total":49,"time":2471.997,"pts_sprint":13,"pts_kom":0,"tempo_pos":9,"tempo_time":2471.997,"tempo_points":49,"sprinter_pos":9,"sprinter_total_race_points":49},{"category":"E","name":"Francisco Duarte (PTG) (ZOSS VOG team)","tname":"ZOSS VOG","zwid":1891183,"pos":10,"fal":2,"fts":5,"fin":32,"total":39,"time":2635.822,"pts_sprint":7,"pts_kom":0,"tempo_pos":10,"tempo_time":2635.822,"tempo_points":39,"sprinter_pos":11,"sprinter_total_race_points":39},{"category":"E","name":"Jorge A. Letras","tname":"","zwid":3289864,"pos":11,"fal":4,"fts":4,"fin":0,"total":8,"time":0,"pts_sprint":8,"pts_kom":0,"tempo_pos":11,"tempo_time":0,"tempo_points":8,"sprinter_pos":10,"sprinter_total_race_points":8}]}